building/__init__.py
building/admin.py
building/apps.py
building/build_log.py
building/models.py
building/permission.py
building/select.py
building/serializers.py
building/status.py
building/tests.py
building/utils.py
building/views.py
building/migrations/__init__.py
django_building-0.0.3.dist-info/LICENSE
django_building-0.0.3.dist-info/METADATA
django_building-0.0.3.dist-info/WHEEL
django_building-0.0.3.dist-info/top_level.txt
django_building-0.0.3.dist-info/RECORD
